<keymap version="1" name="XWin copy" parent="Default for XWin">
  <action id="ActivateDatabaseToolWindow">
    <keyboard-shortcut first-keystroke="alt t" />
    <keyboard-shortcut first-keystroke="alt 2" />
  </action>
  <action id="ActivateFavoritesToolWindow" />
  <action id="ActivateTerminalToolWindow">
    <keyboard-shortcut first-keystroke="alt f12" />
    <keyboard-shortcut first-keystroke="ctrl alt t" />
  </action>
  <action id="CloseContent">
    <keyboard-shortcut first-keystroke="ctrl f4" />
    <keyboard-shortcut first-keystroke="ctrl w" />
  </action>
  <action id="EditorSelectWord">
    <keyboard-shortcut first-keystroke="alt d" />
  </action>
  <action id="FileStructurePopup">
    <keyboard-shortcut first-keystroke="ctrl f12" />
    <keyboard-shortcut first-keystroke="alt r" />
  </action>
  <action id="GotoAction">
    <keyboard-shortcut first-keystroke="shift ctrl a" />
    <keyboard-shortcut first-keystroke="alt p" />
  </action>
  <action id="NewElement">
    <keyboard-shortcut first-keystroke="alt insert" />
    <keyboard-shortcut first-keystroke="alt c" />
  </action>
  <action id="SelectAllOccurrences">
    <keyboard-shortcut first-keystroke="shift ctrl alt j" />
    <keyboard-shortcut first-keystroke="alt a" />
  </action>
  <action id="ServiceView.GroupByContributor" />
  <action id="ShowNavBar">
    <keyboard-shortcut first-keystroke="alt home" />
    <keyboard-shortcut first-keystroke="alt n" />
  </action>
  <action id="SmartSelect" />
  <action id="SurroundWith" />
  <action id="TableResult.GrowSelection" />
  <action id="UsageGrouping.UsageType" />
</keymap>